{
  "model_type": "Ensemble (GBM + XGBoost[Optuna] + LightGBM[Optuna] + CatBoost) + Ridge stacking",
  "prediction_target": "DDG (kcal/mol)",
  "n_models": 4,
  "use_stacking": true,
  "n_features": 58,
  "feature_version": "v8_extended_biochemical",
  "condition_features": {
    "feature_49": "temperature_C (assay temperature from ThermoMutDB/FireProtDB)",
    "feature_50": "pH (assay pH from ThermoMutDB/FireProtDB)",
    "feature_51": "dMW (molecular weight delta)",
    "feature_52": "dHbond_donors",
    "feature_53": "dHbond_acceptors",
    "feature_54": "dTurn_propensity",
    "feature_55": "polarity_change",
    "feature_56": "charge_gain",
    "feature_57": "charge_loss",
    "feature_58": "delta_ionization (pH-dependent)"
  },
  "training_samples": 8905,
  "stabilizing_samples": 4912,
  "destabilizing_samples": 3993,
  "data_sources": {
    "FireProtDB": 3402,
    "ProDDG": 0,
    "ThermoMutDB": 5503
  },
  "synthetic_data": false,
  "independent_test_set": "S669 (669 mutations)",
  "cv_mae": 1.08,
  "cv_r2": 0.4802,
  "cv_pearson": 0.693,
  "cv_spearman": 0.6765,
  "cv_accuracy": 0.7652,
  "cv_f1": 0.8005,
  "test_mae": 0.0,
  "test_rmse": 0.0,
  "test_r2": 0.0,
  "test_pearson_r": 0.0,
  "test_spearman_r": 0.0,
  "test_accuracy": 0.0,
  "test_f1": 0.0,
  "test_auc": 0.0,
  "deltaTm_regressor": {
    "n_training_samples": 4953,
    "source": "ThermoMutDB (Pucci et al. 2021)",
    "cv_mae_celsius": 4.6119,
    "cv_pearson": 0.5225,
    "cv_spearman": 0.4638,
    "dtm_range": [
      -68.0,
      45.0
    ]
  }
}