{
  "model_type": "v23: 8-model ensemble + wide-stack clf + real RSA/SS + PSSM + ESM-2 PCA-32 + metal coord + ionic strength + Debye-H\u00fcckel/Born physics + C\u03b1 contact number + B-factor z-score + ESM-2 \u0394LL (134 features)",
  "prediction_target": "DDG (kcal/mol)",
  "n_models": 6,
  "use_stacking": true,
  "meta_type": "GBM",
  "optimal_threshold": 0.006253295349541162,
  "n_features": 134,
  "feature_version": "v10_cross_terms",
  "condition_features": {
    "feature_49": "temperature_C (assay temperature from ThermoMutDB/FireProtDB)",
    "feature_50": "pH (assay pH from ThermoMutDB/FireProtDB)",
    "feature_51": "dMW (molecular weight delta)",
    "feature_52": "dHbond_donors",
    "feature_53": "dHbond_acceptors",
    "feature_54": "dTurn_propensity",
    "feature_55": "polarity_change",
    "feature_56": "charge_gain",
    "feature_57": "charge_loss",
    "feature_58": "delta_ionization (pH-dependent)"
  },
  "training_samples": 17791,
  "stabilizing_samples": 8780,
  "destabilizing_samples": 9011,
  "data_sources": {
    "FireProtDB": 6798,
    "ProDDG": 0,
    "ThermoMutDB": 10993
  },
  "synthetic_data": false,
  "independent_test_set": "S669 (669 mutations)",
  "cv_mae": 0.9449,
  "cv_r2": 0.5917,
  "cv_pearson": 0.7697,
  "cv_spearman": 0.6891,
  "cv_accuracy": 0.7798,
  "cv_f1": 0.7783,
  "test_mae": 0.0,
  "test_rmse": 0.0,
  "test_r2": 0.0,
  "test_pearson_r": 0.0,
  "test_spearman_r": 0.0,
  "test_accuracy": 0.0,
  "test_f1": 0.0,
  "test_auc": 0.0,
  "deltaTm_regressor": {
    "n_training_samples": 4953,
    "source": "ThermoMutDB (Pucci et al. 2021)",
    "cv_mae_celsius": 3.8987,
    "cv_pearson": 0.645,
    "cv_spearman": 0.6344,
    "dtm_range": [
      -68.0,
      45.0
    ]
  }
}